{"id": 21, "ocr_v": 1, "title": "ข้าน้อยสมควรตาย Big Ass", "vocab": ["Am", "C", "Dm", "Em", "F", "G"], "skel": [{"lyric": true, "indent": 0, "text": "โลกใบนี้ เหมือนมีคำสาบให้คน ทุกคนทำสิ่งต้องห้าม ก็รู้ว่าไม่ดี"}, {"lyric": true, "indent": 0, "text": "จะผิดขนาดไหน หัวใจก็ยังดื้อรั้น ไม่รู้ว่าทำไมยังดื้อด้าน เลวสิ้นดี"}, {"blank": true}, {"lyric": true, "indent": 0, "text": "* คิดจะไปเป็นมือที่สาม มันก็ควรต้องโดนซักที"}, {"blank": true}, {"lyric": true, "indent": 4, "text": "** ฉันไม่ได้อยากเลว ไม่อยากทำอย่างนี้ มันผิดจริงๆ ก็พอรู้ตัวดี ได้แต่โทษทีที่ฉันทำไป"}, {"blank": true}, {"lyric": true, "indent": 9, "text": "ฉันไม่ได้อยากเลว แค่หยุดใจ ไม่ไหว มันผิดจริงๆ อย่างนี้สมควรตาย แต่จะให้ทำยังไง ก็ทั้งหัวใจ รักเธอ"}, {"blank": true}, {"lyric": true, "indent": 0, "text": "คนเป็นล้าน หัวใจทำไมไม่รัก ก็เหลือคนยังโสดตั้งมาก ไปรับเข้ามาซิ"}, {"blank": true}, {"lyric": true, "indent": 0, "text": "มันผิดเข้าใจไหม หัวใจทำไมไม่ฟัง ก็รู้ ใจของเธอมันไม่ว่าง ดูบ้างซิ"}, {"blank": true}, {"lyric": true, "indent": 0, "text": "ก็จะให้ทำยังไง ก็ทั้งหัวใจ ยังรักเธอ"}], "sung": ["โลกใบนี้ เหมือนมีคำสาบให้คน ทุกคนทำสิ่งต้องห้าม ก็รู้ว่าไม่ดี", "จะผิดขนาดไหน หัวใจก็ยังดื้อรั้น ไม่รู้ว่าทำไมยังดื้อด้าน เลวสิ้นดี", "* คิดจะไปเป็นมือที่สาม มันก็ควรต้องโดนซักที", "** ฉันไม่ได้อยากเลว ไม่อยากทำอย่างนี้ มันผิดจริงๆ ก็พอรู้ตัวดี ได้แต่โทษทีที่ฉันทำไป", "ฉันไม่ได้อยากเลว แค่หยุดใจ ไม่ไหว มันผิดจริงๆ อย่างนี้สมควรตาย แต่จะให้ทำยังไง ก็ทั้งหัวใจ รักเธอ", "คนเป็นล้าน หัวใจทำไมไม่รัก ก็เหลือคนยังโสดตั้งมาก ไปรับเข้ามาซิ", "มันผิดเข้าใจไหม หัวใจทำไมไม่ฟัง ก็รู้ ใจของเธอมันไม่ว่าง ดูบ้างซิ", "ก็จะให้ทำยังไง ก็ทั้งหัวใจ ยังรักเธอ"], "fast": false, "en1": [{"text": "Tune down Vz tone to Eb", "x0": 6.5, "x1": 162.5, "cx": 84.5, "yc": 13.5, "conf": 0.5}, {"text": "Am", "x0": 65.0, "x1": 90.0, "cx": 77.5, "yc": 57.8, "conf": 1.0}, {"text": "F", "x0": 168.0, "x1": 175.5, "cx": 171.8, "yc": 57.0, "conf": 1.0}, {"text": "Dm", "x0": 267.0, "x1": 292.0, "cx": 279.5, "yc": 57.5, "conf": 1.0}, {"text": "F  g", "x0": 334.0, "x1": 369.0, "cx": 351.5, "yc": 57.2, "conf": 0.3}, {"text": "Tanlui IwiijutianNnuIvAU  vnAwVaugijviin1  fz77I1igi", "x0": 18.5, "x1": 334.0, "cx": 176.2, "yc": 70.8, "conf": 0.0}, {"text": "Am", "x0": 74.5, "x1": 100.5, "cx": 87.5, "yc": 86.5, "conf": 1.0}, {"text": "F", "x0": 171.5, "x1": 180.5, "cx": 176.0, "yc": 86.2, "conf": 1.0}, {"text": "Dm", "x0": 271.5, "x1": 298.0, "cx": 284.8, "yc": 86.8, "conf": 1.0}, {"text": "F", "x0": 336.0, "x1": 350.0, "cx": 343.0, "yc": 85.8, "conf": 1.0}, {"text": "g", "x0": 365.0, "x1": 379.0, "cx": 372.0, "yc": 86.0, "conf": 0.4}, {"text": "~JYMgNu7 wu   wlanjjgjzu YizinvIujgdgnu  1n7nug", "x0": 18.5, "x1": 349.0, "cx": 183.8, "yc": 99.5, "conf": 0.0}, {"text": "Dm", "x0": 68.0, "x1": 95.0, "cx": 81.5, "yc": 129.8, "conf": 1.0}, {"text": "Em", "x0": 124.0, "x1": 147.5, "cx": 135.8, "yc": 129.8, "conf": 1.0}, {"text": "F", "x0": 182.5, "x1": 193.0, "cx": 187.8, "yc": 129.5, "conf": 1.0}, {"text": "g", "x0": 253.0, "x1": 265.0, "cx": 259.0, "yc": 129.5, "conf": 0.8}, {"text": "*Agaludubvin74    nAnsbinvTguunvi", "x0": 43.0, "x1": 275.5, "cx": 159.2, "yc": 143.5, "conf": 0.1}, {"text": "C", "x0": 121.0, "x1": 134.0, "cx": 127.5, "yc": 173.2, "conf": 0.3}, {"text": "Am", "x0": 243.5, "x1": 269.0, "cx": 256.2, "yc": 173.5, "conf": 1.0}, {"text": "F", "x0": 352.5, "x1": 362.5, "cx": 357.5, "yc": 173.0, "conf": 1.0}, {"text": "Dm", "x0": 380.0, "x1": 407.0, "cx": 393.5, "yc": 173.8, "conf": 1.0}, {"text": "g", "x0": 448.0, "x1": 460.0, "cx": 454.0, "yc": 174.0, "conf": 0.7}, {"text": "**", "x0": 56.5, "x1": 75.5, "cx": 66.0, "yc": 184.5, "conf": 0.5}, {"text": "du lu\"lsnunninn YvaunnvhaxnJi", "x0": 73.5, "x1": 261.5, "cx": 167.5, "yc": 186.2, "conf": 0.0}, {"text": "Ihatig93J91 fMajohg", "x0": 269.0, "x1": 382.0, "cx": 325.5, "yc": 187.0, "conf": 0.0}, {"text": "'rlciTv1tvvauv- u", "x0": 394.0, "x1": 513.0, "cx": 453.5, "yc": 186.0, "conf": 0.1}, {"text": "C", "x0": 116.0, "x1": 130.0, "cx": 123.0, "yc": 202.0, "conf": 0.9}, {"text": "Am", "x0": 229.5, "x1": 255.0, "cx": 242.2, "yc": 202.0, "conf": 1.0}, {"text": "F", "x0": 349.5, "x1": 359.5, "cx": 354.5, "yc": 202.5, "conf": 1.0}, {"text": "Dm", "x0": 401.0, "x1": 428.0, "cx": 414.5, "yc": 202.8, "conf": 1.0}, {"text": "g", "x0": 475.0, "x1": 488.0, "cx": 481.5, "yc": 202.5, "conf": 0.9}, {"text": "du9llgwu7nin7 IAwUG?v Ilw7  Ifi93J9 0x7vi31A50J  UGiaivivn8y\"IJ fVjiv %nlsz", "x0": 65.5, "x1": 582.0, "cx": 323.8, "yc": 215.8, "conf": 0.0}, {"text": "Instru / C /", "x0": 18.5, "x1": 98.0, "cx": 58.2, "yc": 245.5, "conf": 0.7}, {"text": "Am", "x0": 53.5, "x1": 79.0, "cx": 66.2, "yc": 274.0, "conf": 1.0}, {"text": "F", "x0": 150.0, "x1": 159.5, "cx": 154.8, "yc": 274.5, "conf": 1.0}, {"text": "Dm", "x0": 260.0, "x1": 285.0, "cx": 272.5, "yc": 274.0, "conf": 1.0}, {"text": "F  G", "x0": 358.0, "x1": 392.5, "cx": 375.2, "yc": 274.0, "conf": 0.7}, {"text": "Auduznu wnlavlu\"liin fIwRjAujJTzockjln '1julz7173", "x0": 17.5, "x1": 358.0, "cx": 187.8, "yc": 288.8, "conf": 0.0}, {"text": "Am", "x0": 83.0, "x1": 108.0, "cx": 95.5, "yc": 303.8, "conf": 1.0}, {"text": "F", "x0": 177.5, "x1": 187.5, "cx": 182.5, "yc": 303.5, "conf": 1.0}, {"text": "Dm", "x0": 291.5, "x1": 317.5, "cx": 304.5, "yc": 303.8, "conf": 1.0}, {"text": "F  g", "x0": 353.5, "x1": 393.5, "cx": 373.5, "yc": 303.0, "conf": 0.4}, {"text": "1ung1xnl9lu Wlavhlu hw 7 {anjvisorulliinJ QU72", "x0": 17.5, "x1": 356.5, "cx": 187.0, "yc": 318.2, "conf": 0.0}, {"text": "(*,**)", "x0": 17.0, "x1": 76.5, "cx": 46.8, "yc": 347.8, "conf": 1.0}, {"text": "Instru", "x0": 18.5, "x1": 64.0, "cx": 41.2, "yc": 376.5, "conf": 1.0}, {"text": "'{845483", "x0": 54.0, "x1": 143.0, "cx": 98.5, "yc": 383.5, "conf": 0.0}, {"text": "Times )", "x0": 134.5, "x1": 183.5, "cx": 159.0, "yc": 377.0, "conf": 1.0}, {"text": "1G /", "x0": 135.0, "x1": 171.5, "cx": 153.2, "yc": 391.2, "conf": 0.7}, {"text": "(*,**)", "x0": 17.0, "x1": 77.5, "cx": 47.2, "yc": 419.5, "conf": 1.0}, {"text": "F  G", "x0": 15.5, "x1": 60.0, "cx": 37.8, "yc": 462.8, "conf": 0.6}, {"text": "Em", "x0": 116.5, "x1": 140.5, "cx": 128.5, "yc": 462.5, "conf": 1.0}, {"text": "Dm", "x0": 173.0, "x1": 200.0, "cx": 186.5, "yc": 462.8, "conf": 1.0}, {"text": "C", "x0": 222.0, "x1": 236.0, "cx": 229.0, "yc": 462.0, "conf": 0.9}, {"text": "halivhtjJ ivjwniv Jjinigj", "x0": 57.5, "x1": 240.0, "cx": 148.8, "yc": 475.8, "conf": 0.0}, {"text": "Www.chordtabs in.th", "x0": 344.5, "x1": 541.0, "cx": 442.8, "yc": 483.5, "conf": 0.4}], "en2": [{"text": "Tune down Vz tone to Eb", "x0": 5.7, "x1": 163.0, "cx": 84.3, "yc": 13.3, "conf": 0.9}, {"text": "Am", "x0": 63.7, "x1": 91.0, "cx": 77.3, "yc": 57.7, "conf": 1.0}, {"text": "F", "x0": 167.3, "x1": 176.3, "cx": 171.8, "yc": 57.3, "conf": 1.0}, {"text": "Dm_", "x0": 265.7, "x1": 292.7, "cx": 279.2, "yc": 57.3, "conf": 1.0}, {"text": "F G", "x0": 324.7, "x1": 370.7, "cx": 347.7, "yc": 56.8, "conf": 0.6}, {"text": "Taniut  IWiaufifn uIviAU  vnnunaudiduvinu  63in'uig", "x0": 17.7, "x1": 335.3, "cx": 176.5, "yc": 70.8, "conf": 0.0}, {"text": "Am", "x0": 74.0, "x1": 101.0, "cx": 87.5, "yc": 86.8, "conf": 1.0}, {"text": "F", "x0": 170.7, "x1": 180.3, "cx": 175.5, "yc": 86.5, "conf": 1.0}, {"text": "Dm", "x0": 270.7, "x1": 298.0, "cx": 284.3, "yc": 86.7, "conf": 1.0}, {"text": "F   G", "x0": 334.7, "x1": 380.7, "cx": 357.7, "yc": 86.0, "conf": 0.4}, {"text": "~aqqunq wu", "x0": 18.7, "x1": 99.7, "cx": 59.2, "yc": 100.0, "conf": 0.1}, {"text": "wnlanuba-u   'IliziM'Iu8ugagu", "x0": 103.7, "x1": 299.0, "cx": 201.3, "yc": 99.7, "conf": 0.0}, {"text": "Innnug", "x0": 302.7, "x1": 349.7, "cx": 326.2, "yc": 99.0, "conf": 0.1}, {"text": "Dm", "x0": 68.0, "x1": 95.0, "cx": 81.5, "yc": 129.5, "conf": 1.0}, {"text": "Em", "x0": 122.7, "x1": 147.7, "cx": 135.2, "yc": 129.5, "conf": 1.0}, {"text": "F", "x0": 181.0, "x1": 192.7, "cx": 186.8, "yc": 129.0, "conf": 1.0}, {"text": "G", "x0": 252.0, "x1": 265.7, "cx": 258.8, "yc": 129.5, "conf": 0.3}, {"text": "\"Aqaxluldufova7l  IunnnsbinvTquanvi", "x0": 42.0, "x1": 276.0, "cx": 159.0, "yc": 143.2, "conf": 0.0}, {"text": "C", "x0": 121.0, "x1": 134.7, "cx": 127.8, "yc": 173.5, "conf": 0.4}, {"text": "Am", "x0": 243.0, "x1": 269.7, "cx": 256.3, "yc": 173.7, "conf": 1.0}, {"text": "F", "x0": 350.7, "x1": 363.7, "cx": 357.2, "yc": 173.2, "conf": 1.0}, {"text": "Dm", "x0": 379.7, "x1": 407.0, "cx": 393.3, "yc": 173.3, "conf": 1.0}, {"text": "g", "x0": 447.3, "x1": 460.7, "cx": 454.0, "yc": 173.5, "conf": 0.6}, {"text": "##", "x0": 56.0, "x1": 75.7, "cx": 65.8, "yc": 184.3, "conf": 0.4}, {"text": "~auI\"lojunnin?  'iaxnnmaxinvi\"", "x0": 72.7, "x1": 262.3, "cx": 167.5, "yc": 186.7, "conf": 0.0}, {"text": "~4ufigQ5u9 6Maj6ng", "x0": 268.7, "x1": 382.7, "cx": 325.7, "yc": 187.5, "conf": 0.0}, {"text": "lciTv1vivaum lz", "x0": 393.0, "x1": 514.0, "cx": 453.5, "yc": 186.7, "conf": 0.1}, {"text": "C", "x0": 116.0, "x1": 131.0, "cx": 123.5, "yc": 202.5, "conf": 0.3}, {"text": "Am", "x0": 229.0, "x1": 256.0, "cx": 242.5, "yc": 202.7, "conf": 1.0}, {"text": "F", "x0": 348.3, "x1": 360.0, "cx": 354.2, "yc": 201.8, "conf": 1.0}, {"text": "Dm", "x0": 401.0, "x1": 428.0, "cx": 414.5, "yc": 202.3, "conf": 1.0}, {"text": "6", "x0": 474.7, "x1": 488.3, "cx": 481.5, "yc": 202.7, "conf": 0.4}, {"text": "au\"uj\"loounnian Ilrvug?v %lw?", "x0": 65.3, "x1": 252.7, "cx": 159.0, "yc": 216.5, "conf": 0.0}, {"text": "Ihaiga5Jq auniquan50U  IGavimtvlJ fvJin?? 5nlsz", "x0": 256.0, "x1": 582.7, "cx": 419.3, "yc": 215.5, "conf": 0.0}, {"text": "Instru / C /", "x0": 17.3, "x1": 98.3, "cx": 57.8, "yc": 245.7, "conf": 0.8}, {"text": "Am", "x0": 52.7, "x1": 80.0, "cx": 66.3, "yc": 274.5, "conf": 1.0}, {"text": "F", "x0": 149.3, "x1": 159.7, "cx": 154.5, "yc": 274.0, "conf": 1.0}, {"text": "Dm", "x0": 258.7, "x1": 286.0, "cx": 272.3, "yc": 274.3, "conf": 1.0}, {"text": "F G", "x0": 349.3, "x1": 394.7, "cx": 372.0, "yc": 274.2, "conf": 0.7}, {"text": "Audlurnu ila'u\"hiin fIwabauTjTzooiuln 'I1jui7n17&", "x0": 17.0, "x1": 359.0, "cx": 188.0, "yc": 288.7, "conf": 0.0}, {"text": "Am", "x0": 81.7, "x1": 108.7, "cx": 95.2, "yc": 303.7, "conf": 1.0}, {"text": "F", "x0": 178.0, "x1": 187.3, "cx": 182.7, "yc": 303.0, "conf": 1.0}, {"text": "Dm", "x0": 290.7, "x1": 318.0, "cx": 304.3, "yc": 303.3, "conf": 0.9}, {"text": "CF G", "x0": 340.7, "x1": 395.0, "cx": 367.8, "yc": 302.7, "conf": 0.2}, {"text": "sufiqirinlalwu wlav'lu\"uii n3 {a83JlgaruhninJ qun3", "x0": 16.7, "x1": 356.7, "cx": 186.7, "yc": 317.8, "conf": 0.0}, {"text": "(* ,**)", "x0": 18.0, "x1": 77.3, "cx": 47.7, "yc": 347.5, "conf": 0.7}, {"text": "Instru", "x0": 17.7, "x1": 63.0, "cx": 40.3, "yc": 376.5, "conf": 1.0}, {"text": "'{8954923", "x0": 53.3, "x1": 141.0, "cx": 97.2, "yc": 383.8, "conf": 0.1}, {"text": "Times )", "x0": 133.7, "x1": 183.3, "cx": 158.5, "yc": 377.0, "conf": 1.0}, {"text": "Dm / G /", "x0": 111.3, "x1": 172.0, "cx": 141.7, "yc": 390.8, "conf": 1.0}, {"text": "(*,**)", "x0": 17.3, "x1": 77.3, "cx": 47.3, "yc": 419.5, "conf": 0.7}, {"text": "F   G", "x0": 15.3, "x1": 60.3, "cx": 37.8, "yc": 461.5, "conf": 0.5}, {"text": "Em", "x0": 115.7, "x1": 140.7, "cx": 128.2, "yc": 462.5, "conf": 1.0}, {"text": "Dm", "x0": 172.3, "x1": 200.3, "cx": 186.3, "yc": 462.3, "conf": 1.0}, {"text": "~c", "x0": 216.3, "x1": 237.3, "cx": 226.8, "yc": 462.5, "conf": 0.2}, {"text": "haxlivjuI iwuwnl? JJsnisj", "x0": 56.7, "x1": 240.7, "cx": 148.7, "yc": 476.2, "conf": 0.1}, {"text": "WWW chordtabs in.th", "x0": 343.7, "x1": 542.0, "cx": 442.8, "yc": 483.2, "conf": 0.7}], "th": [{"text": "โลกใบนี้  เหมือนมีศาสาบใท้คน ทกคนฟาลิ่งต้องทามกิรว่าไม่ดี", "x0": 18.5, "x1": 334.0, "cx": 176.2, "yc": 70.8, "conf": 0.2}, {"text": "ฉะผิดขนาดไหน ฺฟาใจก็ยังดือรัน ไม่ร้วาฬาไมยังดือด้าน เลาสินดี", "x0": 18.5, "x1": 349.0, "cx": 183.8, "yc": 99.5, "conf": 0.2}, {"text": "*คิดจะไปเป็นมือท้สาม  มันก็คารต้องโดนอักที", "x0": 43.0, "x1": 275.5, "cx": 159.2, "yc": 143.5, "conf": 0.1}, {"text": "ฉันไม่ได้อยากเลา 'ไม่อยากฟาอย่างนี", "x0": 73.5, "x1": 261.5, "cx": 167.5, "yc": 186.2, "conf": 0.2}, {"text": "มันผิดจริงฯ เกีพอร์ต้าดี", "x0": 269.0, "x1": 382.0, "cx": 325.5, "yc": 187.0, "conf": 0.3}, {"text": "ได้แต่โทษทีทีนันฟาไป", "x0": 394.0, "x1": 513.0, "cx": 453.5, "yc": 186.0, "conf": 0.3}, {"text": "นัน'ไม่ได้อยากเลว  แค่ทยุดใจ ไม่ไทว  มันผิดจริงๆ อย่างนี้สมคารตายแต่าะให้ท่ายังไง เกีฬั้งฟ้าใจ รักเธอ", "x0": 65.5, "x1": 582.0, "cx": 323.8, "yc": 215.8, "conf": 0.0}, {"text": "คนเป็นล้านฟ้าใจฟาไม่'ไม่รัก  กีเหลือคนยังโสดตั้งมากไปรับเข้ามาซี", "x0": 17.5, "x1": 358.0, "cx": 187.8, "yc": 288.8, "conf": 0.3}, {"text": "มันผิดเข้าใจไทมฺฟ้าใจฟา'ไม'ไม่ขัง กีรใจของเธอมัน'ไม่ว่างดูบ้างซี", "x0": 17.5, "x1": 356.5, "cx": 187.0, "yc": 318.2, "conf": 0.1}, {"text": "เกิจะใท้ฟายังไจ เกิ่ฬังหาใจฮังรักเธอ", "x0": 57.5, "x1": 240.0, "cx": 148.8, "yc": 475.8, "conf": 0.1}, {"text": "wwพ. chordtabs.in. th", "x0": 344.5, "x1": 541.0, "cx": 442.8, "yc": 483.5, "conf": 0.2}]}